autoform/__init__.py
autoform/ad.py
autoform/batch.py
autoform/control.py
autoform/core.py
autoform/harvest.py
autoform/lm.py
autoform/optims.py
autoform/string.py
autoform/utils.py
autoform-0.0.6.dist-info/licenses/LICENSE
autoform-0.0.6.dist-info/METADATA
autoform-0.0.6.dist-info/WHEEL
autoform-0.0.6.dist-info/top_level.txt
autoform-0.0.6.dist-info/RECORD
