Metadata-Version: 2.4
Name: autoform
Version: 0.0.6
Summary: Composable function transformations for LLM programs
Requires-Python: >=3.12
License-File: LICENSE
Requires-Dist: litellm>=1.80.9
Requires-Dist: optree>=0.18.0
Dynamic: license-file
